{
  "updated_at": "2026-01-31T07:43:41+00:00",
  "queues": [
    {
      "id": "1853",
      "name": "A/B Amagervold - Ekstern venteliste",
      "position": 390,
      "total": 446,
      "active": false,
      "completed": true,
      "approved": true,
      "start_position": 431,
      "moved": 41,
      "moved_pct": 9.51,
      "progress": {
        "week": 31
      }
    },
    {
      "id": "1737",
      "name": "A/B Buddingevej - Ekstern venteliste",
      "position": 52,
      "total": 55,
      "active": false,
      "completed": true,
      "approved": true,
      "start_position": 53,
      "moved": 1,
      "moved_pct": 1.89,
      "progress": {
        "week": 0
      }
    },
    {
      "id": "392",
      "name": "A/B Baghuset - Ekstern venteliste",
      "position": 327,
      "total": 334,
      "active": false,
      "completed": true,
      "approved": true,
      "start_position": 332,
      "moved": 5,
      "moved_pct": 1.51,
      "progress": {
        "week": 1
      }
    },
    {
      "id": "41",
      "name": "A/B Gl Kongevej 35 A - 37 A - Ekstern venteliste",
      "position": 642,
      "total": 678,
      "active": false,
      "completed": true,
      "approved": true,
      "start_position": 655,
      "moved": 13,
      "moved_pct": 1.98,
      "progress": {
        "week": 2
      }
    },
    {
      "id": "294",
      "name": "A/B Positiv - Ekstern venteliste",
      "position": 759,
      "total": 776,
      "active": false,
      "completed": true,
      "approved": true,
      "start_position": 771,
      "moved": 12,
      "moved_pct": 1.56,
      "progress": {
        "week": 4
      }
    },
    {
      "id": "966",
      "name": "A/B Vesterbrogade 176 / Kochsvej 44-46 - Ekstern venteliste",
      "position": 249,
      "total": 250,
      "active": false,
      "completed": true,
      "approved": true,
      "start_position": 249,
      "moved": 0,
      "moved_pct": 0.0,
      "progress": {
        "week": 0
      }
    }
  ],
  "sitemap_kbh": {
    "updated_at": "2026-01-31T07:43:29+00:00",
    "source": "https://waitly.eu/da/sitemap",
    "initialized": false,
    "total_urls": 292,
    "new_count": 0,
    "new": []
  }
}